chefmate/__init__.py
chefmate/browser_manager.py
chefmate/chefmate_core.py
chefmate/cli.py
chefmate/config.py
chefmate-1.0.3.dist-info/licenses/LICENSE
chefmate-1.0.3.dist-info/METADATA
chefmate-1.0.3.dist-info/WHEEL
chefmate-1.0.3.dist-info/entry_points.txt
chefmate-1.0.3.dist-info/top_level.txt
chefmate-1.0.3.dist-info/RECORD
