Metadata-Version: 2.4
Name: chefmate
Version: 1.0.3
Summary: Automation tool for CodeChef
Home-page: https://github.com/Anuj-72/ChefMate
Author: Anuj Kumar Sah
Author-email: Anuj Kumar Sah <anujsah282005@gmail.com>
License: MIT
Keywords: CodeChef,CLI,automation,competitive-programming
Classifier: Programming Language :: Python :: 3
Classifier: License :: OSI Approved :: MIT License
Classifier: Operating System :: OS Independent
Classifier: Intended Audience :: Developers
Classifier: Topic :: Software Development :: Build Tools
Requires-Python: >=3.7
License-File: LICENSE
Requires-Dist: selenium
Requires-Dist: webdriver-manager
Requires-Dist: click
Requires-Dist: colorama
Requires-Dist: inquirer
Requires-Dist: InquirerPy
Requires-Dist: rich
Requires-Dist: tabulate
Requires-Dist: pandas
Dynamic: author
Dynamic: home-page
Dynamic: license-file
Dynamic: requires-python
